[
  {
    "museum": "中国国家博物馆",
    "title": "涅瓦河畔的遐思——列宾艺术特展",
    "hall": "南3、南4展厅",
    "publish_time": "2025/7/23—2026/1/11",
    "detail_url": "https://www.chnmuseum.cn/zl/lszl/gjjlxl/202507/t20250709_272123.shtml",
    "column_id": "网上展览"
  },
  {
    "museum": "中国国家博物馆",
    "title": "文明的星河——上海合作组织国家博物馆藏文物联展",
    "hall": "北1、北2展厅",
    "publish_time": "2025/8/27—11/16",
    "detail_url": "https://www.chnmuseum.cn/zl/lszl/gjjlxl/202508/t20250826_272532.shtml",
    "column_id": "网上展览"
  },
  {
    "museum": "中国国家博物馆",
    "title": "王国的艺术——沙特阿拉伯当代艺术展",
    "hall": "北3、北4展厅",
    "publish_time": "2025/7/31—10/30",
    "detail_url": "https://www.chnmuseum.cn/zl/lszl/gjjlxl/202507/t20250729_272280.shtml",
    "column_id": "网上展览"
  },
  {
    "museum": "中国国家博物馆",
    "title": "宇宙考古：时空探索",
    "hall": "北8展厅",
    "publish_time": "2025/7/2—10/12",
    "detail_url": "https://www.chnmuseum.cn/zl/lszl/gjjlxl/202506/t20250624_271967.shtml",
    "column_id": "网上展览"
  },
  {
    "museum": "中国国家博物馆",
    "title": "琉光璃彩——淄博琉璃艺术展",
    "hall": "南6、南7展厅",
    "publish_time": "2025/6/10—10/8",
    "detail_url": "https://www.chnmuseum.cn/zl/lszl/dywhxl/202506/t20250609_271879.shtml",
    "column_id": "网上展览"
  },
  {
    "museum": "中国国家博物馆",
    "title": "美的多元——古希腊的艺术与生活",
    "hall": "南1、南2展厅",
    "publish_time": "2024/11/6—2025/9/5",
    "detail_url": "https://www.chnmuseum.cn/zl/lszl/gjjlxl/202410/t20241021_270354.shtml",
    "column_id": "网上展览"
  },
  {
    "museum": "中国国家博物馆",
    "title": "青春之歌——全国大学生创新成果展",
    "hall": "",
    "publish_time": "2025/4/29—6/22",
    "detail_url": "https://www.chnmuseum.cn/zl/lszl/kjcxz/202504/t20250425_271527.shtml",
    "column_id": "网上展览"
  },
  {
    "museum": "中国国家博物馆",
    "title": "石韵天成——中国观赏石艺术展",
    "hall": "北4展厅",
    "publish_time": "2025/5/13—6/14",
    "detail_url": "https://www.chnmuseum.cn/zl/lszl/lswhxl/202505/t20250508_271619.shtml",
    "column_id": "网上展览"
  },
  {
    "museum": "中国国家博物馆",
    "title": "九天揽月——中国探月工程20年",
    "hall": "南6、南7展厅",
    "publish_time": "2025/4/1—5/25",
    "detail_url": "https://www.chnmuseum.cn/zl/lszl/kjcxz/202503/t20250328_271353.shtml",
    "column_id": "网上展览"
  },
  {
    "museum": "中国国家博物馆",
    "title": "（当日可...网络发展新图景成就展",
    "hall": "南4展厅",
    "publish_time": "2025/2/20—5/11",
    "detail_url": "https://www.chnmuseum.cn/zl/lszl/kjcxz/202502/t20250221_271124.shtml",
    "column_id": "网上展览"
  },
  {
    "museum": "中国国家博物馆",
    "title": "四海一堂春——乙巳蛇年新春文化展",
    "hall": "北4展厅",
    "publish_time": "2025/1/22—4/22",
    "detail_url": "https://www.chnmuseum.cn/zl/lszl/lswhxl/202501/t20250117_270915.shtml",
    "column_id": "网上展览"
  },
  {
    "museum": "中国国家博物馆",
    "title": "万古长歌——湖南史前文明图卷展",
    "hall": "北3展厅",
    "publish_time": "2025/2/20—3/27",
    "detail_url": "https://www.chnmuseum.cn/zl/lszl/dywhxl/202501/t20250122_270937.shtml",
    "column_id": "网上展览"
  }
]